MANIFEST.in
README.md
setup.cfg
setup.py
vodkas/__init__.py
vodkas/apex3d.py
vodkas/default_paths.py
vodkas/fs.py
vodkas/iadbs.py
vodkas/misc.py
vodkas/peptide3d.py
vodkas.egg-info/PKG-INFO
vodkas.egg-info/SOURCES.txt
vodkas.egg-info/dependency_links.txt
vodkas.egg-info/top_level.txt
vodkas/examples/__init__.py
vodkas/examples/process_raw_data.py