Metadata-Version: 1.1
Name: vodkas
Version: 0.0.1
Summary: Syntactic sugar around Waters LC/IMS/MS pypeline.
Home-page: https://github.com/MatteoLacki/vodkas
Author: Mateusz Krzysztof Łącki
Author-email: matteo.lacki@gmail.com
License: UNKNOWN
Keywords: Mass Spectrometry,WatersSymphony Pipeline,Going Insane
Platform: UNKNOWN
Classifier: Development Status :: 1 - Planning
Classifier: License :: OSI Approved :: BSD License
Classifier: Intended Audience :: Science/Research
Classifier: Topic :: Scientific/Engineering :: Chemistry
Classifier: Programming Language :: Python :: 3.6
